iam_policy/__init__.py
iam_policy/aws/__init__.py
iam_policy/aws/aws_iam_policy_builder.py
iam_policy/gcp/__init__.py
iam_policy/gcp/gcp_iam_policy_builder.py
python_iam_policy_builder-0.1.6.dist-info/licenses/LICENSE
python_iam_policy_builder-0.1.6.dist-info/METADATA
python_iam_policy_builder-0.1.6.dist-info/WHEEL
python_iam_policy_builder-0.1.6.dist-info/top_level.txt
python_iam_policy_builder-0.1.6.dist-info/RECORD
