Metadata-Version: 2.4
Name: python-iam-policy-builder
Version: 0.1.6
Summary: A fluent Python IAM Policy builder
Author-email: Omer Menashe <unspecified@mail.com>
License: MIT
Project-URL: Source, https://github.com/iamomerm/python-iam-policy-builder
Keywords: python-iam-policy-builder,iam-policy,iam
Classifier: Programming Language :: Python :: 3
Classifier: License :: OSI Approved :: MIT License
Classifier: Operating System :: OS Independent
Requires-Python: >=3.7
License-File: LICENSE
Dynamic: license-file
